ComparisonUnit/comp_top.v
module comp_top(
    input [15:0]in0, in1,
    input is_signed,
    output reg GT, LT, ET
    );

    always @(*)begin

        GT = 0;
        LT = 0;
        ET = 0;

        if (~is_signed)begin
            GT = (in0 > in1);
            LT = (in0 < in1);
            ET = (in0 == in1);
        end else begin
            if (in0[15] == 0 && in1[15] == 1)begin
                GT = 1;
                LT = 0;
                ET = 0;
            end else if (in0[15] == 1 && in1[15] == 0)begin
                GT = 0;
                LT = 1;
                ET = 0;
            end else if (in0[15] == 1 && in1[15] == 1)begin
                GT = ~(in0 < in1);
                LT = ~(in0 > in1);
                ET = (in0 == in1);
            end else begin
                GT = (in0 > in1);
                LT = (in0 < in1);
                ET = (in0 == in1);
            end
        end
    end
endmodule

ComparisonUnit/tb_comp_top.v
`timescale 1ns/1ps

module tb_comp_top();

    reg [15:0]in0;
    reg [15:0]in1;
    reg is_signed;
    wire GT;
    wire LT;
    wire ET;

    comp_top uut (
        .in0(in0),
        .in1(in1),
        .is_signed(is_signed),
        .GT(GT),
        .LT(LT),
        .ET(ET)
    );

    initial begin
        $dumpfile("comparisonwaveform.vcd");
        $dumpvars(0, tb_comp_top);

        is_signed = 0; #10;
        in0 = 16'd5; in1 = 16'd3; #10;
        $display("input 1 = %d input 2 = %d || GT = %b || LT = %b || ET = %b", in0, in1, GT, LT, ET);
        in0 = 16'd3; in1 = 16'd10; #10;
        $display("input 1 = %d input 2 = %d || GT = %b || LT = %b || ET = %b", in0, in1, GT, LT, ET);
        in0 = 16'd7; in1 = 16'd7; #10;
        $display("input 1 = %d input 2 = %d || GT = %b || LT = %b || ET = %b", in0, in1, GT, LT, ET);
        is_signed = 1; #10;
        in0 = -16'sd1; in1 = 16'd5; #10;
        $display("input 1 = %d input 2 = %d || GT = %b || LT = %b || ET = %b", in0, in1, GT, LT, ET);
        in0 = 16'd5; in1 = -16'sd1; #10;
        $display("input 1 = %d input 2 = %d || GT = %b || LT = %b || ET = %b", in0, in1, GT, LT, ET);
        in0 = -16'sd2; in1 = -16'sd5; #10;
        $display("input 1 = %d input 2 = %d || GT = %b || LT = %b || ET = %b", in0, in1, GT, LT, ET);
        in0 = -16'sd5; in1 = -16'sd2; #10;
        $display("input 1 = %d input 2 = %d || GT = %b || LT = %b || ET = %b", in0, in1, GT, LT, ET);
        in0 = 16'd10; in1 = 16'd2; #10;
        $display("input 1 = %d input 2 = %d || GT = %b || LT = %b || ET = %b", in0, in1, GT, LT, ET);
        $finish;
    end
endmodule

comparisonwaveform.vcd
$date
	Thu Jul 31 21:12:42 2025
$end
$version
	Icarus Verilog
$end
$timescale
	1ps
$end
$scope module tb_comp_top $end
$var wire 1 ! LT $end
$var wire 1 " GT $end
$var wire 1 # ET $end
$var reg 16 $ in0 [15:0] $end
$var reg 16 % in1 [15:0] $end
$var reg 1 & is_signed $end
$scope module uut $end
$var wire 16 ' in0 [15:0] $end
$var wire 16 ( in1 [15:0] $end
$var wire 1 & is_signed $end
$var reg 1 # ET $end
$var reg 1 " GT $end
$var reg 1 ! LT $end
$upscope $end
$upscope $end
$enddefinitions $end
$comment Show the parameter values. $end
$dumpall
$end
#0
$dumpvars
bx (
bx '
0&
bx %
bx $
x#
x"
x!
$end
#10000
0#
0!
1"
b11 %
b11 (
b101 $
b101 '
#20000
1!
0"
b1010 %
b1010 (
b11 $
b11 '
#30000
1#
0!
b111 %
b111 (
b111 $
b111 '
#40000
1#
1&
#50000
1!
0#
b101 %
b101 (
b1111111111111111 $
b1111111111111111 '
#60000
1"
0!
b1111111111111111 %
b1111111111111111 (
b101 $
b101 '
#70000
1"
b1111111111111011 %
b1111111111111011 (
b1111111111111110 $
b1111111111111110 '
#80000
1!
0"
b1111111111111110 %
b1111111111111110 (
b1111111111111011 $
b1111111111111011 '
#90000
1"
0!
b10 %
b10 (
b1010 $
b1010 '
