LogicUnit/gate_xnor.v
module gate_xnor(
    input [15:0]in0, in1,
    output [15:0]xnor_out
)   ;
    assign xnor_out = ~(in0 ^ in1);
endmodule

LogicUnit/gate_nor.v
module gate_nor(
    input [15:0]in0, in1,
    output [15:0]nor_out
    );
    assign nor_out = ~(in0 | in1);
endmodule

LogicUnit/gate_nand.v
module gate_nand(
    input [15:0]in0, in1,
    output [15:0]nand_out
    );
    assign nand_out = ~(in0 & in1);
endmodule

LogicUnit/gate_not.v
module gate_not(
    input [15:0]in0, in1,
    output [15:0]not_out
    );
    assign not_out = ~in0;
endmodule

LogicUnit/gate_xor.v
module gate_xor(
    input [15:0]in0, in1,
    output [15:0]xor_out
    );
    assign xor_out = in0 ^ in1;
endmodule

LogicUnit/gate_or.v
module gate_or(
    input [15:0]in0, in1,
    output [15:0]or_out
    );
    assign or_out = in0 | in1;
endmodule

LogicUnit/gate_and.v
module gate_and(
    input [15:0]in0, in1,
    output [15:0]and_out
    );
    assign and_out = in0 & in1;
endmodule

LogicUnit/logic_top.v
module logic_top(
    input [2:0]sel,
    input [15:0]in0,
    input [15:0]in1,
    output [15:0]and_out,
    output [15:0]or_out,
    output [15:0]xor_out,
    output [15:0]not_out,
    output [15:0]nand_out,
    output [15:0]nor_out,
    output [15:0]xnor_out,
    output reg [15:0]result
    );

    gate_and andmodule (
        .in0(in0),
        .in1(in1),
        .and_out(and_out)
    );
    gate_or ormodule (
        .in0(in0),
        .in1(in1),
        .or_out(or_out)
    );
    gate_xor xormodule (
        .in0(in0),
        .in1(in1),
        .xor_out(xor_out)
    );
    gate_not notmodule (
        .in0(in0),
        .in1(in1),
        .not_out(not_out)
    );
    gate_nand nandmodule (
        .in0(in0),
        .in1(in1),
        .nand_out(nand_out)
    );
    gate_nor normodule (
        .in0(in0),
        .in1(in1),
        .nor_out(nor_out)
    );
    gate_xnor xnormodule (
        .in0(in0),
        .in1(in1),
        .xnor_out(xnor_out)
    );

    always @(*)begin
        case(sel)
            3'b000: result = and_out;
            3'b001: result = or_out;
            3'b010: result = xor_out;
            3'b011: result = not_out;
            3'b100: result = nand_out;
            3'b101: result = nor_out;
            3'b110: result = xnor_out;
            3'b111: result = 16'd0;
        endcase
    end
endmodule

LogicUnit/tb_logic_top.v
`timescale 1ns/1ps

module tb_logic_top();
    reg [15:0]in0;
    reg [15:0]in1;
    wire [15:0]result;
    reg [2:0]sel;

    logic_top uut (
        .in0(in0),
        .in1(in1),
        .sel(sel),
        .result(result)
    );

    initial begin
        $dumpfile("logicwaveform.vcd");
        $dumpvars(0, tb_logic_top);

        sel = 3'b000;
        in0 = 0;
        in1 = 0;
        #10;
        $display("sel = %b || in1 = %b in2 = %b || result = %b", sel, in0, in1, result);
        sel = 3'b000;
        in0 = 0;
        in1 = 1;
        #10;
        $display("sel = %b || in1 = %b in2 = %b || result = %b", sel, in0, in1, result);
        sel = 3'b000;
        in0 = 1;
        in1 = 0;
        #10;
        $display("sel = %b || in1 = %b in2 = %b || result = %b", sel, in0, in1, result);
        sel = 3'b000;
        in0 = 1;
        in1 = 1;
        #10;
        $display("sel = %b || in1 = %b in2 = %b || result = %b", sel, in0, in1, result);

        sel = 3'b001;
        in0 = 0;
        in1 = 0;
        #10;
        $display("sel = %b || in1 = %b in2 = %b || result = %b", sel, in0, in1, result);
        sel = 3'b001;
        in0 = 0;
        in1 = 1;
        #10;
        $display("sel = %b || in1 = %b in2 = %b || result = %b", sel, in0, in1, result);
        sel = 3'b001;
        in0 = 1;
        in1 = 0;
        #10;
        $display("sel = %b || in1 = %b in2 = %b || result = %b", sel, in0, in1, result);
        sel = 3'b001;
        in0 = 1;
        in1 = 1;
        #10;
        $display("sel = %b || in1 = %b in2 = %b || result = %b", sel, in0, in1, result);

        sel = 3'b010;
        in0 = 0;
        in1 = 0;
        #10;
        $display("sel = %b || in1 = %b in2 = %b || result = %b", sel, in0, in1, result);
        sel = 3'b010;
        in0 = 0;
        in1 = 1;
        #10;
        $display("sel = %b || in1 = %b in2 = %b || result = %b", sel, in0, in1, result);
        sel = 3'b010;
        in0 = 1;
        in1 = 0;
        #10;
        $display("sel = %b || in1 = %b in2 = %b || result = %b", sel, in0, in1, result);
        sel = 3'b010;
        in0 = 1;
        in1 = 1;
        #10;
        $display("sel = %b || in1 = %b in2 = %b || result = %b", sel, in0, in1, result);

        sel = 3'b011;
        in0 = 0;
        in1 = 0;
        #10;
        $display("sel = %b || in1 = %b in2 = %b || result = %b", sel, in0, in1, result);
        sel = 3'b011;
        in0 = 0;
        in1 = 1;
        #10;
        $display("sel = %b || in1 = %b in2 = %b || result = %b", sel, in0, in1, result);
        sel = 3'b011;
        in0 = 1;
        in1 = 0;
        #10;
        $display("sel = %b || in1 = %b in2 = %b || result = %b", sel, in0, in1, result);
        sel = 3'b011;
        in0 = 1;
        in1 = 1;
        #10;
        $display("sel = %b || in1 = %b in2 = %b || result = %b", sel, in0, in1, result);

        sel = 3'b100;
        in0 = 0;
        in1 = 0;
        #10;
        $display("sel = %b || in1 = %b in2 = %b || result = %b", sel, in0, in1, result);
        sel = 3'b100;
        in0 = 0;
        in1 = 1;
        #10;
        $display("sel = %b || in1 = %b in2 = %b || result = %b", sel, in0, in1, result);
        sel = 3'b100;
        in0 = 1;
        in1 = 0;
        #10;
        $display("sel = %b || in1 = %b in2 = %b || result = %b", sel, in0, in1, result);
        sel = 3'b100;
        in0 = 1;
        in1 = 1;
        #10;
        $display("sel = %b || in1 = %b in2 = %b || result = %b", sel, in0, in1, result);

        sel = 3'b101;
        in0 = 0;
        in1 = 0;
        #10;
        $display("sel = %b || in1 = %b in2 = %b || result = %b", sel, in0, in1, result);
        sel = 3'b101;
        in0 = 0;
        in1 = 1;
        #10;
        $display("sel = %b || in1 = %b in2 = %b || result = %b", sel, in0, in1, result);
        sel = 3'b101;
        in0 = 1;
        in1 = 0;
        #10;
        $display("sel = %b || in1 = %b in2 = %b || result = %b", sel, in0, in1, result);
        sel = 3'b101;
        in0 = 1;
        in1 = 1;
        #10;
        $display("sel = %b || in1 = %b in2 = %b || result = %b", sel, in0, in1, result);

        sel = 3'b110;
        in0 = 0;
        in1 = 0;
        #10;
        $display("sel = %b || in1 = %b in2 = %b || result = %b", sel, in0, in1, result);
        sel = 3'b110;
        in0 = 0;
        in1 = 1;
        #10;
        $display("sel = %b || in1 = %b in2 = %b || result = %b", sel, in0, in1, result);
        sel = 3'b110;
        in0 = 1;
        in1 = 0;
        #10;
        $display("sel = %b || in1 = %b in2 = %b || result = %b", sel, in0, in1, result);
        sel = 3'b110;
        in0 = 1;
        in1 = 1;
        #10;
        $display("sel = %b || in1 = %b in2 = %b || result = %b", sel, in0, in1, result);

        sel = 3'b111;
        in0 = 0;
        in1 = 0;
        #10;
        $display("sel = %b || in1 = %b in2 = %b || result = %b", sel, in0, in1, result);
        sel = 3'b111;
        in0 = 0;
        in1 = 1;
        #10;
        $display("sel = %b || in1 = %b in2 = %b || result = %b", sel, in0, in1, result);
        sel = 3'b111;
        in0 = 1;
        in1 = 0;
        #10;
        $display("sel = %b || in1 = %b in2 = %b || result = %b", sel, in0, in1, result);
        sel = 3'b111;
        in0 = 1;
        in1 = 1;
        #10;
        $display("sel = %b || in1 = %b in2 = %b || result = %b", sel, in0, in1, result);
        $finish;
    end
endmodule

logicwaveform.vcd
$date
	Tue Jul 29 00:50:35 2025
$end
$version
	Icarus Verilog
$end
$timescale
	1ps
$end
$scope module tb_logic_top $end
$var wire 16 ! result [15:0] $end
$var reg 16 " in0 [15:0] $end
$var reg 16 # in1 [15:0] $end
$var reg 3 $ sel [2:0] $end
$scope module uut $end
$var wire 16 % in0 [15:0] $end
$var wire 16 & in1 [15:0] $end
$var wire 3 ' sel [2:0] $end
$var wire 16 ( xor_out [15:0] $end
$var wire 16 ) xnor_out [15:0] $end
$var wire 16 * or_out [15:0] $end
$var wire 16 + not_out [15:0] $end
$var wire 16 , nor_out [15:0] $end
$var wire 16 - nand_out [15:0] $end
$var wire 16 . and_out [15:0] $end
$var reg 16 / result [15:0] $end
$scope module andmodule $end
$var wire 16 0 and_out [15:0] $end
$var wire 16 1 in0 [15:0] $end
$var wire 16 2 in1 [15:0] $end
$upscope $end
$scope module nandmodule $end
$var wire 16 3 in0 [15:0] $end
$var wire 16 4 in1 [15:0] $end
$var wire 16 5 nand_out [15:0] $end
$upscope $end
$scope module normodule $end
$var wire 16 6 in0 [15:0] $end
$var wire 16 7 in1 [15:0] $end
$var wire 16 8 nor_out [15:0] $end
$upscope $end
$scope module notmodule $end
$var wire 16 9 in0 [15:0] $end
$var wire 16 : in1 [15:0] $end
$var wire 16 ; not_out [15:0] $end
$upscope $end
$scope module ormodule $end
$var wire 16 < in0 [15:0] $end
$var wire 16 = in1 [15:0] $end
$var wire 16 > or_out [15:0] $end
$upscope $end
$scope module xnormodule $end
$var wire 16 ? in0 [15:0] $end
$var wire 16 @ in1 [15:0] $end
$var wire 16 A xnor_out [15:0] $end
$upscope $end
$scope module xormodule $end
$var wire 16 B in0 [15:0] $end
$var wire 16 C in1 [15:0] $end
$var wire 16 D xor_out [15:0] $end
$upscope $end
$upscope $end
$upscope $end
$enddefinitions $end
$comment Show the parameter values. $end
$dumpall
$end
#0
$dumpvars
b0 D
b0 C
b0 B
b1111111111111111 A
b0 @
b0 ?
b0 >
b0 =
b0 <
b1111111111111111 ;
b0 :
b0 9
b1111111111111111 8
b0 7
b0 6
b1111111111111111 5
b0 4
b0 3
b0 2
b0 1
b0 0
b0 /
b0 .
b1111111111111111 -
b1111111111111111 ,
b1111111111111111 +
b0 *
b1111111111111111 )
b0 (
b0 '
b0 &
b0 %
b0 $
b0 #
b0 "
b0 !
$end
#10000
b1111111111111110 ,
b1111111111111110 8
b1111111111111110 )
b1111111111111110 A
b1 *
b1 >
b1 (
b1 D
b1 #
b1 &
b1 2
b1 4
b1 7
b1 :
b1 =
b1 @
b1 C
#20000
b1111111111111110 +
b1111111111111110 ;
b0 #
b0 &
b0 2
b0 4
b0 7
b0 :
b0 =
b0 @
b0 C
b1 "
b1 %
b1 1
b1 3
b1 6
b1 9
b1 <
b1 ?
b1 B
#30000
b1111111111111110 -
b1111111111111110 5
b1111111111111111 )
b1111111111111111 A
b1 !
b1 /
b1 .
b1 0
b0 (
b0 D
b1 #
b1 &
b1 2
b1 4
b1 7
b1 :
b1 =
b1 @
b1 C
#40000
b1111111111111111 -
b1111111111111111 5
b1111111111111111 ,
b1111111111111111 8
b0 !
b0 /
b0 .
b0 0
b1111111111111111 +
b1111111111111111 ;
b0 *
b0 >
b0 #
b0 &
b0 2
b0 4
b0 7
b0 :
b0 =
b0 @
b0 C
b0 "
b0 %
b0 1
b0 3
b0 6
b0 9
b0 <
b0 ?
b0 B
b1 $
b1 '
#50000
b1111111111111110 ,
b1111111111111110 8
b1111111111111110 )
b1111111111111110 A
b1 !
b1 /
b1 *
b1 >
b1 (
b1 D
b1 #
b1 &
b1 2
b1 4
b1 7
b1 :
b1 =
b1 @
b1 C
#60000
b1111111111111110 +
b1111111111111110 ;
b0 #
b0 &
b0 2
b0 4
b0 7
b0 :
b0 =
b0 @
b0 C
b1 "
b1 %
b1 1
b1 3
b1 6
b1 9
b1 <
b1 ?
b1 B
#70000
b1111111111111110 -
b1111111111111110 5
b1111111111111111 )
b1111111111111111 A
b1 .
b1 0
b0 (
b0 D
b1 #
b1 &
b1 2
b1 4
b1 7
b1 :
b1 =
b1 @
b1 C
#80000
b1111111111111111 -
b1111111111111111 5
b1111111111111111 ,
b1111111111111111 8
b0 .
b0 0
b1111111111111111 +
b1111111111111111 ;
b0 *
b0 >
b0 !
b0 /
b0 #
b0 &
b0 2
b0 4
b0 7
b0 :
b0 =
b0 @
b0 C
b0 "
b0 %
b0 1
b0 3
b0 6
b0 9
b0 <
b0 ?
b0 B
b10 $
b10 '
#90000
b1111111111111110 ,
b1111111111111110 8
b1111111111111110 )
b1111111111111110 A
b1 !
b1 /
b1 *
b1 >
b1 (
b1 D
b1 #
b1 &
b1 2
b1 4
b1 7
b1 :
b1 =
b1 @
b1 C
#100000
b1111111111111110 +
b1111111111111110 ;
b0 #
b0 &
b0 2
b0 4
b0 7
b0 :
b0 =
b0 @
b0 C
b1 "
b1 %
b1 1
b1 3
b1 6
b1 9
b1 <
b1 ?
b1 B
#110000
b1111111111111110 -
b1111111111111110 5
b1111111111111111 )
b1111111111111111 A
b0 !
b0 /
b1 .
b1 0
b0 (
b0 D
b1 #
b1 &
b1 2
b1 4
b1 7
b1 :
b1 =
b1 @
b1 C
#120000
b1111111111111111 -
b1111111111111111 5
b1111111111111111 ,
b1111111111111111 8
b0 .
b0 0
b1111111111111111 +
b1111111111111111 ;
b0 *
b0 >
b1111111111111111 !
b1111111111111111 /
b0 #
b0 &
b0 2
b0 4
b0 7
b0 :
b0 =
b0 @
b0 C
b0 "
b0 %
b0 1
b0 3
b0 6
b0 9
b0 <
b0 ?
b0 B
b11 $
b11 '
#130000
b1111111111111110 ,
b1111111111111110 8
b1111111111111110 )
b1111111111111110 A
b1 *
b1 >
b1 (
b1 D
b1 #
b1 &
b1 2
b1 4
b1 7
b1 :
b1 =
b1 @
b1 C
#140000
b1111111111111110 !
b1111111111111110 /
b1111111111111110 +
b1111111111111110 ;
b0 #
b0 &
b0 2
b0 4
b0 7
b0 :
b0 =
b0 @
b0 C
b1 "
b1 %
b1 1
b1 3
b1 6
b1 9
b1 <
b1 ?
b1 B
#150000
b1111111111111110 -
b1111111111111110 5
b1111111111111111 )
b1111111111111111 A
b1 .
b1 0
b0 (
b0 D
b1 #
b1 &
b1 2
b1 4
b1 7
b1 :
b1 =
b1 @
b1 C
#160000
b1111111111111111 !
b1111111111111111 /
b1111111111111111 -
b1111111111111111 5
b1111111111111111 ,
b1111111111111111 8
b0 .
b0 0
b1111111111111111 +
b1111111111111111 ;
b0 *
b0 >
b0 #
b0 &
b0 2
b0 4
b0 7
b0 :
b0 =
b0 @
b0 C
b0 "
b0 %
b0 1
b0 3
b0 6
b0 9
b0 <
b0 ?
b0 B
b100 $
b100 '
#170000
b1111111111111110 ,
b1111111111111110 8
b1111111111111110 )
b1111111111111110 A
b1 *
b1 >
b1 (
b1 D
b1 #
b1 &
b1 2
b1 4
b1 7
b1 :
b1 =
b1 @
b1 C
#180000
b1111111111111110 +
b1111111111111110 ;
b0 #
b0 &
b0 2
b0 4
b0 7
b0 :
b0 =
b0 @
b0 C
b1 "
b1 %
b1 1
b1 3
b1 6
b1 9
b1 <
b1 ?
b1 B
#190000
b1111111111111110 !
b1111111111111110 /
b1111111111111110 -
b1111111111111110 5
b1111111111111111 )
b1111111111111111 A
b1 .
b1 0
b0 (
b0 D
b1 #
b1 &
b1 2
b1 4
b1 7
b1 :
b1 =
b1 @
b1 C
#200000
b1111111111111111 !
b1111111111111111 /
b1111111111111111 -
b1111111111111111 5
b1111111111111111 ,
b1111111111111111 8
b0 .
b0 0
b1111111111111111 +
b1111111111111111 ;
b0 *
b0 >
b0 #
b0 &
b0 2
b0 4
b0 7
b0 :
b0 =
b0 @
b0 C
b0 "
b0 %
b0 1
b0 3
b0 6
b0 9
b0 <
b0 ?
b0 B
b101 $
b101 '
#210000
b1111111111111110 !
b1111111111111110 /
b1111111111111110 ,
b1111111111111110 8
b1111111111111110 )
b1111111111111110 A
b1 *
b1 >
b1 (
b1 D
b1 #
b1 &
b1 2
b1 4
b1 7
b1 :
b1 =
b1 @
b1 C
#220000
b1111111111111110 +
b1111111111111110 ;
b0 #
b0 &
b0 2
b0 4
b0 7
b0 :
b0 =
b0 @
b0 C
b1 "
b1 %
b1 1
b1 3
b1 6
b1 9
b1 <
b1 ?
b1 B
#230000
b1111111111111110 -
b1111111111111110 5
b1111111111111111 )
b1111111111111111 A
b1 .
b1 0
b0 (
b0 D
b1 #
b1 &
b1 2
b1 4
b1 7
b1 :
b1 =
b1 @
b1 C
#240000
b1111111111111111 -
b1111111111111111 5
b1111111111111111 ,
b1111111111111111 8
b0 .
b0 0
b1111111111111111 +
b1111111111111111 ;
b0 *
b0 >
b1111111111111111 !
b1111111111111111 /
b0 #
b0 &
b0 2
b0 4
b0 7
b0 :
b0 =
b0 @
b0 C
b0 "
b0 %
b0 1
b0 3
b0 6
b0 9
b0 <
b0 ?
b0 B
b110 $
b110 '
#250000
b1111111111111110 !
b1111111111111110 /
b1111111111111110 ,
b1111111111111110 8
b1111111111111110 )
b1111111111111110 A
b1 *
b1 >
b1 (
b1 D
b1 #
b1 &
b1 2
b1 4
b1 7
b1 :
b1 =
b1 @
b1 C
#260000
b1111111111111110 +
b1111111111111110 ;
b0 #
b0 &
b0 2
b0 4
b0 7
b0 :
b0 =
b0 @
b0 C
b1 "
b1 %
b1 1
b1 3
b1 6
b1 9
b1 <
b1 ?
b1 B
#270000
b1111111111111111 !
b1111111111111111 /
b1111111111111110 -
b1111111111111110 5
b1111111111111111 )
b1111111111111111 A
b1 .
b1 0
b0 (
b0 D
b1 #
b1 &
b1 2
b1 4
b1 7
b1 :
b1 =
b1 @
b1 C
#280000
b1111111111111111 -
b1111111111111111 5
b1111111111111111 ,
b1111111111111111 8
b0 .
b0 0
b1111111111111111 +
b1111111111111111 ;
b0 *
b0 >
b0 !
b0 /
b0 #
b0 &
b0 2
b0 4
b0 7
b0 :
b0 =
b0 @
b0 C
b0 "
b0 %
b0 1
b0 3
b0 6
b0 9
b0 <
b0 ?
b0 B
b111 $
b111 '
#290000
b1111111111111110 ,
b1111111111111110 8
b1111111111111110 )
b1111111111111110 A
b1 *
b1 >
b1 (
b1 D
b1 #
b1 &
b1 2
b1 4
b1 7
b1 :
b1 =
b1 @
b1 C
#300000
b1111111111111110 +
b1111111111111110 ;
b0 #
b0 &
b0 2
b0 4
b0 7
b0 :
b0 =
b0 @
b0 C
b1 "
b1 %
b1 1
b1 3
b1 6
b1 9
b1 <
b1 ?
b1 B
#310000
b1111111111111110 -
b1111111111111110 5
b1111111111111111 )
b1111111111111111 A
b1 .
b1 0
b0 (
b0 D
b1 #
b1 &
b1 2
b1 4
b1 7
b1 :
b1 =
b1 @
b1 C
