ShiftingUnit/shifting_top.v
module shifting_top(
    input [15:0]in0,
    input [3:0]in1,
    input [2:0]shift_type,
    output reg [15:0]shift_result
    );

    always @(*)begin
        case (shift_type)
            3'b000: shift_result = in0 << in1;
            3'b001: shift_result = in0 >> in1;
            3'b010: shift_result = in0 <<< in1;
            3'b011:begin
                if (~in0[15])begin
                    shift_result = in0 >>> in1;
                end else begin
                    shift_result = in0 >>> in1;
                    shift_result = (in0 >> in1) | (16'hFFF << (16-in1)); //Used masked logic here. Forces 1s instead of 0s.
                end
            end
            3'b100:begin
                shift_result = (in0 << in1) | (in0 >> (16-in1));
            end
            3'b101:begin
                shift_result = (in0 >> in1) | (in0 << (16-in1));
            end
            3'b110: shift_result = 16'b0;//Empty case
            3'b111: shift_result = 16'b0;//Empty case
        endcase
    end
endmodule

ShiftingUnit/tb_shifting_top.v
`timescale 1ns/1ps

module tb_shifting_top();
    reg [15:0]in0;
    reg [3:0]in1;
    reg [2:0]shift_type;
    wire [15:0]shift_result;

    shifting_top uut (
        .in0(in0),
        .in1(in1),
        .shift_result(shift_result),
        .shift_type(shift_type)
    );

    initial begin
        $dumpfile("shiftingwaveform.vcd");
        $dumpvars(0, tb_shifting_top);

        in0 = 16'h0000; in1 = 4'd0;  shift_type = 3'b000; #10;
        $display("Input number: %b || Shifted by: %b || Shift type: %b || Output: %b ||", in0, in1, shift_type, shift_result);
        in0 = 16'h0001; in1 = 4'd1;  shift_type = 3'b000; #10;
        $display("Input number: %b || Shifted by: %b || Shift type: %b || Output: %b ||", in0, in1, shift_type, shift_result);
        in0 = 16'h8000; in1 = 4'd15; shift_type = 3'b000; #10;
        $display("Input number: %b || Shifted by: %b || Shift type: %b || Output: %b ||", in0, in1, shift_type, shift_result);
        in0 = 16'h0001; in1 = 4'd15; shift_type = 3'b001; #10;
        $display("Input number: %b || Shifted by: %b || Shift type: %b || Output: %b ||", in0, in1, shift_type, shift_result);
        in0 = 16'hF000; in1 = 4'd4;  shift_type = 3'b001; #10;
        $display("Input number: %b || Shifted by: %b || Shift type: %b || Output: %b ||", in0, in1, shift_type, shift_result);
        in0 = 16'hF000; in1 = 4'd1;  shift_type = 3'b010; #10;
        $display("Input number: %b || Shifted by: %b || Shift type: %b || Output: %b ||", in0, in1, shift_type, shift_result);
        in0 = 16'h8000; in1 = 4'd1;  shift_type = 3'b011; #10;
        $display("Input number: %b || Shifted by: %b || Shift type: %b || Output: %b ||", in0, in1, shift_type, shift_result);
        in0 = 16'h7000; in1 = 4'd1;  shift_type = 3'b011; #10;
        $display("Input number: %b || Shifted by: %b || Shift type: %b || Output: %b ||", in0, in1, shift_type, shift_result);
        in0 = 16'h1000; in1 = 4'd1;  shift_type = 3'b100; #10;
        $display("Input number: %b || Shifted by: %b || Shift type: %b || Output: %b ||", in0, in1, shift_type, shift_result);
        in0 = 16'h8001; in1 = 4'd1;  shift_type = 3'b100; #10;
        $display("Input number: %b || Shifted by: %b || Shift type: %b || Output: %b ||", in0, in1, shift_type, shift_result);
        in0 = 16'h0002; in1 = 4'd1;  shift_type = 3'b101; #10;
        $display("Input number: %b || Shifted by: %b || Shift type: %b || Output: %b ||", in0, in1, shift_type, shift_result);
        in0 = 16'h0003; in1 = 4'd1;  shift_type = 3'b101; #10;
        $display("Input number: %b || Shifted by: %b || Shift type: %b || Output: %b ||", in0, in1, shift_type, shift_result);
        in0 = 16'hF000; in1 = 4'd1;  shift_type = 3'b110; #10;
        $display("Input number: %b || Shifted by: %b || Shift type: %b || Output: %b ||", in0, in1, shift_type, shift_result);
        in0 = 16'h0001; in1 = 4'd1;  shift_type = 3'b111; #10;
        $display("Input number: %b || Shifted by: %b || Shift type: %b || Output: %b ||", in0, in1, shift_type, shift_result);
        in0 = 16'h8000; in1 = 4'd1;  shift_type = 3'b011; #10;
        $display("Input number: %b || Shifted by: %b || Shift type: %b || Output: %b ||", in0, in1, shift_type, shift_result);
        in0 = 16'h7000; in1 = 4'd1;  shift_type = 3'b011; #10;
        $display("Input number: %b || Shifted by: %b || Shift type: %b || Output: %b ||", in0, in1, shift_type, shift_result);
        $finish;
    end
endmodule

shiftingwaveform.vcd
$date
	Fri Aug 01 01:23:26 2025
$end
$version
	Icarus Verilog
$end
$timescale
	1ps
$end
$scope module tb_shifting_top $end
$var wire 16 ! shift_result [15:0] $end
$var reg 16 " in0 [15:0] $end
$var reg 4 # in1 [3:0] $end
$var reg 3 $ shift_type [2:0] $end
$scope module uut $end
$var wire 16 % in0 [15:0] $end
$var wire 4 & in1 [3:0] $end
$var wire 3 ' shift_type [2:0] $end
$var reg 16 ( shift_result [15:0] $end
$upscope $end
$upscope $end
$enddefinitions $end
$comment Show the parameter values. $end
$dumpall
$end
#0
$dumpvars
b0 (
b0 '
b0 &
b0 %
b0 $
b0 #
b0 "
b0 !
$end
#10000
b10 !
b10 (
b1 #
b1 &
b1 "
b1 %
#20000
b0 !
b0 (
b1111 #
b1111 &
b1000000000000000 "
b1000000000000000 %
#30000
b1 $
b1 '
b1 "
b1 %
#40000
b111100000000 !
b111100000000 (
b100 #
b100 &
b1111000000000000 "
b1111000000000000 %
#50000
b1110000000000000 !
b1110000000000000 (
b10 $
b10 '
b1 #
b1 &
#60000
b1100000000000000 !
b1100000000000000 (
b11 $
b11 '
b1000000000000000 "
b1000000000000000 %
#70000
b11100000000000 !
b11100000000000 (
b111000000000000 "
b111000000000000 %
#80000
b10000000000000 !
b10000000000000 (
b100 $
b100 '
b1000000000000 "
b1000000000000 %
#90000
b11 !
b11 (
b1000000000000001 "
b1000000000000001 %
#100000
b1 !
b1 (
b101 $
b101 '
b10 "
b10 %
#110000
b1000000000000001 !
b1000000000000001 (
b11 "
b11 %
#120000
b0 !
b0 (
b110 $
b110 '
b1111000000000000 "
b1111000000000000 %
#130000
b111 $
b111 '
b1 "
b1 %
#140000
b1100000000000000 !
b1100000000000000 (
b11 $
b11 '
b1000000000000000 "
b1000000000000000 %
#150000
b11100000000000 !
b11100000000000 (
b111000000000000 "
b111000000000000 %
