ArithmeticUnit/unsigned_div.v
module unsigned_div(
    input [15:0]dividend,
    input [15:0]divisor,
    output reg [15:0]quotient, 
    output reg [15:0]remainder
    );

    integer i;
    reg [16:0]remainder_stages[0:16];
    reg [15:0]quotient_stages[0:16];
    reg [16:0]temp_remainder[0:15];
    reg [16:0]temp_sub[0:15];

    always @(*)begin

        remainder_stages[0] = 17'b0;
        quotient_stages[0] = dividend;

        for (i = 0; i < 16; i = i + 1)begin

            temp_remainder[i] = {remainder_stages[i][15:0], quotient_stages[i][15]};
            temp_sub[i] = temp_remainder[i] - {1'b0, divisor};

            if (temp_sub[i][16] == 1'b0)begin
                remainder_stages[i + 1] = temp_sub[i];
                quotient_stages[i + 1] = {quotient_stages[i][14:0], 1'b1};
            end else begin
                remainder_stages[i + 1] = temp_remainder[i];
                quotient_stages[i + 1] = quotient_stages[i] << 1;
            end
        end
        quotient = quotient_stages[16];
        remainder = remainder_stages[16][15:0];
    end
endmodule

ArithmeticUnit/signed_div.v
module signed_div(
    input [15:0]divisor, dividend,
    output reg [15:0]final_quotient, final_remainder
    );

    reg [15:0]temp_divisor;
    reg [15:0]temp_dividend;

    wire [15:0]temp_quotient;
    wire [15:0]temp_remainder;
    wire quotient_sign;
    wire remainder_sign;

    assign quotient_sign = divisor[15] ^ dividend[15];
    assign remainder_sign = dividend[15];

    always @(*)begin
        if(~divisor[15])begin
            temp_divisor = divisor;
        end else begin
            temp_divisor = ~divisor + 1;
        end

        if(~dividend[15])begin
            temp_dividend = dividend;
        end else begin
            temp_dividend = ~dividend + 1;
        end
    end

    unsigned_div unsigneddivisionlogic (
        .dividend(temp_dividend),
        .divisor(temp_divisor),
        .quotient(temp_quotient),
        .remainder(temp_remainder)
    );

    always @(*)begin
        if (~quotient_sign)begin
            final_quotient = temp_quotient;
        end else begin
            final_quotient = ~temp_quotient + 1;
        end

        if (~remainder_sign)begin
            final_remainder = temp_remainder;
        end else begin
            final_remainder = ~temp_remainder + 1;
        end
    end
endmodule

ArithmeticUnit/tb_signed_div.v
`timescale 1ns/1ps

module tb_signed_div();
    reg [15:0]dividend;
    reg [15:0]divisor;
    wire [15:0]final_quotient;
    wire [15:0]final_remainder;

    signed_div uut (
        .dividend(dividend),
        .divisor(divisor),
        .final_quotient(final_quotient),
        .final_remainder(final_remainder)
    );

    initial begin 
        $dumpfile("signedwaveform.vcd");
        $dumpvars(0, tb_signed_div);

        dividend = 16'sd100;
        divisor = 16'sd10;
        #10;
        $display("input 1 = %d input 2 = %d || quotient = %d || remainder = %d", dividend, divisor, final_quotient, final_remainder);

        dividend = -16'sd1000;
        divisor = 16'sd10;
        #10;
        $display("input 1 = %d input 2 = %d || quotient = %d || remainder = %d", dividend, divisor, final_quotient, final_remainder);

        dividend = 16'sd1000;
        divisor = -16'sd10;
        #10;
        $display("input 1 = %d input 2 = %d || quotient = %d || remainder = %d", dividend, divisor, final_quotient, final_remainder);

        dividend = -16'sd1000;
        divisor = -16'sd10;
        #10;
        $display("input 1 = %d input 2 = %d || quotient = %d || remainder = %d", dividend, divisor, final_quotient, final_remainder);

        dividend = 16'sd123;
        divisor = 16'sd1;
        #10;
        $display("input 1 = %d input 2 = %d || quotient = %d || remainder = %d", dividend, divisor, final_quotient, final_remainder);

        dividend = 16'sd123;
        divisor = -16'sd1;
        #10;
        $display("input 1 = %d input 2 = %d || quotient = %d || remainder = %d", dividend, divisor, final_quotient, final_remainder);

        dividend = 16'sd32767;
        divisor = 16'sd2;
        #10;
        $display("input 1 = %d input 2 = %d || quotient = %d || remainder = %d", dividend, divisor, final_quotient, final_remainder);

        dividend = -16'sd32768;
        divisor = -16'sd2;
        #10;
        $display("input 1 = %d input 2 = %d || quotient = %d || remainder = %d", dividend, divisor, final_quotient, final_remainder);

        dividend = 16'sd32767;
        divisor = -16'sd32768;
        #10;
        $display("input 1 = %d input 2 = %d || quotient = %d || remainder = %d", dividend, divisor, final_quotient, final_remainder);

        dividend = 16'sd1234;
        divisor = 16'sd1234;
        #10;
        $display("input 1 = %d input 2 = %d || quotient = %d || remainder = %d", dividend, divisor, final_quotient, final_remainder);

        dividend = 16'sd1234;
        divisor = 16'sd0;
        #10;
        $display("input 1 = %d input 2 = %d || quotient = %d || remainder = %d", dividend, divisor, final_quotient, final_remainder);

        dividend = 16'sd0;
        divisor = 16'sd1234;
        #10;
        $display("input 1 = %d input 2 = %d || quotient = %d || remainder = %d", dividend, divisor, final_quotient, final_remainder);

        $finish;
    end
endmodule

signedwaveform.vcd
$date
	Thu Jul 31 17:13:53 2025
$end
$version
	Icarus Verilog
$end
$timescale
	1ps
$end
$scope module tb_signed_div $end
$var wire 16 ! final_remainder [15:0] $end
$var wire 16 " final_quotient [15:0] $end
$var reg 16 # dividend [15:0] $end
$var reg 16 $ divisor [15:0] $end
$scope module uut $end
$var wire 16 % dividend [15:0] $end
$var wire 16 & divisor [15:0] $end
$var wire 1 ' quotient_sign $end
$var wire 16 ( temp_remainder [15:0] $end
$var wire 16 ) temp_quotient [15:0] $end
$var wire 1 * remainder_sign $end
$var reg 16 + final_quotient [15:0] $end
$var reg 16 , final_remainder [15:0] $end
$var reg 16 - temp_dividend [15:0] $end
$var reg 16 . temp_divisor [15:0] $end
$scope module unsigneddivisionlogic $end
$var wire 16 / dividend [15:0] $end
$var wire 16 0 divisor [15:0] $end
$var reg 16 1 quotient [15:0] $end
$var reg 16 2 remainder [15:0] $end
$var integer 32 3 i [31:0] $end
$upscope $end
$upscope $end
$upscope $end
$enddefinitions $end
$comment Show the parameter values. $end
$dumpall
$end
#0
$dumpvars
b10000 3
b0 2
b1010 1
b1010 0
b1100100 /
b1010 .
b1100100 -
b0 ,
b1010 +
0*
b1010 )
b0 (
0'
b1010 &
b1100100 %
b1010 $
b1100100 #
b1010 "
b0 !
$end
#10000
b1111111110011100 "
b1111111110011100 +
b1100100 )
b1100100 1
b10000 3
1'
b1111101000 -
b1111101000 /
1*
b1111110000011000 #
b1111110000011000 %
#20000
0*
b1111111111110110 $
b1111111111110110 &
b1111101000 #
b1111101000 %
#30000
b1100100 "
b1100100 +
0'
1*
b1111110000011000 #
b1111110000011000 %
#40000
b1111011 "
b1111011 +
b1111011 )
b1111011 1
b10000 3
b1111011 -
b1111011 /
b1 .
b1 0
0*
b1 $
b1 &
b1111011 #
b1111011 %
#50000
b1111111110000101 "
b1111111110000101 +
1'
b1111111111111111 $
b1111111111111111 &
#60000
b1 !
b1 ,
b11111111111111 "
b11111111111111 +
0'
b1 (
b1 2
b11111111111111 )
b11111111111111 1
b10000 3
b111111111111111 -
b111111111111111 /
b10 .
b10 0
b10 $
b10 &
b111111111111111 #
b111111111111111 %
#70000
b100000000000000 "
b100000000000000 +
b0 (
b0 2
b100000000000000 )
b100000000000000 1
b10000 3
b0 !
b0 ,
b1000000000000000 -
b1000000000000000 /
1*
b1111111111111110 $
b1111111111111110 &
b1000000000000000 #
b1000000000000000 %
#80000
b111111111111111 !
b111111111111111 ,
b0 "
b0 +
b111111111111111 (
b111111111111111 2
b0 )
b0 1
b10000 3
1'
b111111111111111 -
b111111111111111 /
b1000000000000000 .
b1000000000000000 0
0*
b1000000000000000 $
b1000000000000000 &
b111111111111111 #
b111111111111111 %
#90000
b0 !
b0 ,
b1 "
b1 +
0'
b0 (
b0 2
b1 )
b1 1
b10000 3
b10011010010 -
b10011010010 /
b10011010010 .
b10011010010 0
b10011010010 $
b10011010010 &
b10011010010 #
b10011010010 %
#100000
b10011010010 !
b10011010010 ,
b1111111111111111 "
b1111111111111111 +
b10011010010 (
b10011010010 2
b1111111111111111 )
b1111111111111111 1
b10000 3
b0 .
b0 0
b0 $
b0 &
#110000
b0 !
b0 ,
b0 "
b0 +
b0 (
b0 2
b0 )
b0 1
b10000 3
b0 -
b0 /
b10011010010 .
b10011010010 0
b10011010010 $
b10011010010 &
b0 #
b0 %
