ArithmeticUnit/unsigned_mult.v
module unsigned_mult(
    input [15:0]in0, in1,
    output [31:0]prod
    );

    wire [15:0]prod1, prod2, prod3, prod4;

    u_mult8bit lxl(.in0(in0[7:0]), .in1(in1[7:0]), .prod(prod1));
    u_mult8bit lxh(.in0(in0[7:0]), .in1(in1[15:8]), .prod(prod2));
    u_mult8bit hxl(.in0(in0[15:8]), .in1(in1[7:0]), .prod(prod3));
    u_mult8bit hxh(.in0(in0[15:8]), .in1(in1[15:8]), .prod(prod4));

    assign prod = prod1 + (prod2 <<8) + (prod3<<8) + (prod4<<16);

endmodule

module u_mult8bit(
    input [7:0]in0, in1,
    output [15:0]prod
    );

    genvar i;
    wire [7:0]mult[0:7];

    generate
        for (i = 0; i < 8; i = i + 1)
            assign mult[i] = {8{in0[i]}} & in1[7:0];
    endgenerate

    assign prod = mult[0] + (mult[1]<<1) + (mult[2]<<2) + (mult[3]<<3) + (mult[4]<<4) + (mult[5]<<5) + (mult[6]<<6) + (mult[7]<<7);
endmodule

ArithmeticUnit/tb_unsigned_mult.v
`timescale 1ns/1ps

module tb_unsigned_mult();
    reg [15:0]in0;
    reg [15:0]in1;
    wire [31:0]prod;

    unsigned_mult uut (
        .in0(in0),
        .in1(in1),
        .prod(prod)
    );

    initial begin
        $dumpfile("unsignedwaveform.vcd");
        $dumpvars(0, tb_unsigned_mult);

        in0 = 16'd0;
        in1 = 16'd0;
        #10;
        $display("input 1 = %b input 2 = %b || product = %b", in0, in1, prod);

        in0 = 16'd1234;
        in1 = 16'd0;
        #10;
        $display("input 1 = %b input 2 = %b || product = %b", in0, in1, prod);

        in0 = 16'd0;
        in1 = 16'd5678;
        #10;
        $display("input 1 = %b input 2 = %b || product = %b", in0, in1, prod);

        in0 = 16'd65535;
        in1 = 16'd1;
        #10;
        $display("input 1 = %b input 2 = %b || product = %b", in0, in1, prod);

        in0 = 16'd1;
        in1 = 16'd65535;
        #10;
        $display("input 1 = %b input 2 = %b || product = %b", in0, in1, prod);

        in0 = 16'd65535;
        in1 = 16'd65535;
        #10;
        $display("input 1 = %b input 2 = %b || product = %b", in0, in1, prod);

        in0 = 16'd2;
        in1 = 16'd2;
        #10;
        $display("input 1 = %b input 2 = %b || product = %b", in0, in1, prod);

        in0 = 16'd256;
        in1 = 16'd256;
        #10;
        $display("input 1 = %b input 2 = %b || product = %b", in0, in1, prod);

        in0 = 16'd1024;
        in1 = 16'd1024;
        #10;
        $display("input 1 = %b input 2 = %b || product = %b", in0, in1, prod);

        in0 = 16'b0101010101010101;
        in1 = 16'b1010101010101010;
        #10;
        $display("input 1 = %b input 2 = %b || product = %b", in0, in1, prod);
        $finish;
    end
endmodule

unsignedwaveform.vcd
$date
	Mon Jul 28 22:32:24 2025
$end
$version
	Icarus Verilog
$end
$timescale
	1ps
$end
$scope module tb_unsigned_mult $end
$var wire 32 ! prod [31:0] $end
$var reg 16 " in0 [15:0] $end
$var reg 16 # in1 [15:0] $end
$scope module uut $end
$var wire 16 $ in0 [15:0] $end
$var wire 16 % in1 [15:0] $end
$var wire 16 & prod4 [15:0] $end
$var wire 16 ' prod3 [15:0] $end
$var wire 16 ( prod2 [15:0] $end
$var wire 16 ) prod1 [15:0] $end
$var wire 32 * prod [31:0] $end
$scope module hxh $end
$var wire 8 + in0 [7:0] $end
$var wire 8 , in1 [7:0] $end
$var wire 16 - prod [15:0] $end
$scope begin genblk1[0] $end
$var parameter 2 . i $end
$upscope $end
$scope begin genblk1[1] $end
$var parameter 2 / i $end
$upscope $end
$scope begin genblk1[2] $end
$var parameter 3 0 i $end
$upscope $end
$scope begin genblk1[3] $end
$var parameter 3 1 i $end
$upscope $end
$scope begin genblk1[4] $end
$var parameter 4 2 i $end
$upscope $end
$scope begin genblk1[5] $end
$var parameter 4 3 i $end
$upscope $end
$scope begin genblk1[6] $end
$var parameter 4 4 i $end
$upscope $end
$scope begin genblk1[7] $end
$var parameter 4 5 i $end
$upscope $end
$upscope $end
$scope module hxl $end
$var wire 8 6 in0 [7:0] $end
$var wire 8 7 in1 [7:0] $end
$var wire 16 8 prod [15:0] $end
$scope begin genblk1[0] $end
$var parameter 2 9 i $end
$upscope $end
$scope begin genblk1[1] $end
$var parameter 2 : i $end
$upscope $end
$scope begin genblk1[2] $end
$var parameter 3 ; i $end
$upscope $end
$scope begin genblk1[3] $end
$var parameter 3 < i $end
$upscope $end
$scope begin genblk1[4] $end
$var parameter 4 = i $end
$upscope $end
$scope begin genblk1[5] $end
$var parameter 4 > i $end
$upscope $end
$scope begin genblk1[6] $end
$var parameter 4 ? i $end
$upscope $end
$scope begin genblk1[7] $end
$var parameter 4 @ i $end
$upscope $end
$upscope $end
$scope module lxh $end
$var wire 8 A in0 [7:0] $end
$var wire 8 B in1 [7:0] $end
$var wire 16 C prod [15:0] $end
$scope begin genblk1[0] $end
$var parameter 2 D i $end
$upscope $end
$scope begin genblk1[1] $end
$var parameter 2 E i $end
$upscope $end
$scope begin genblk1[2] $end
$var parameter 3 F i $end
$upscope $end
$scope begin genblk1[3] $end
$var parameter 3 G i $end
$upscope $end
$scope begin genblk1[4] $end
$var parameter 4 H i $end
$upscope $end
$scope begin genblk1[5] $end
$var parameter 4 I i $end
$upscope $end
$scope begin genblk1[6] $end
$var parameter 4 J i $end
$upscope $end
$scope begin genblk1[7] $end
$var parameter 4 K i $end
$upscope $end
$upscope $end
$scope module lxl $end
$var wire 8 L in0 [7:0] $end
$var wire 8 M in1 [7:0] $end
$var wire 16 N prod [15:0] $end
$scope begin genblk1[0] $end
$var parameter 2 O i $end
$upscope $end
$scope begin genblk1[1] $end
$var parameter 2 P i $end
$upscope $end
$scope begin genblk1[2] $end
$var parameter 3 Q i $end
$upscope $end
$scope begin genblk1[3] $end
$var parameter 3 R i $end
$upscope $end
$scope begin genblk1[4] $end
$var parameter 4 S i $end
$upscope $end
$scope begin genblk1[5] $end
$var parameter 4 T i $end
$upscope $end
$scope begin genblk1[6] $end
$var parameter 4 U i $end
$upscope $end
$scope begin genblk1[7] $end
$var parameter 4 V i $end
$upscope $end
$upscope $end
$upscope $end
$upscope $end
$enddefinitions $end
$comment Show the parameter values. $end
$dumpall
b111 V
b110 U
b101 T
b100 S
b11 R
b10 Q
b1 P
b0 O
b111 K
b110 J
b101 I
b100 H
b11 G
b10 F
b1 E
b0 D
b111 @
b110 ?
b101 >
b100 =
b11 <
b10 ;
b1 :
b0 9
b111 5
b110 4
b101 3
b100 2
b11 1
b10 0
b1 /
b0 .
$end
#0
$dumpvars
b0 N
b0 M
b0 L
b0 C
b0 B
b0 A
b0 8
b0 7
b0 6
b0 -
b0 ,
b0 +
b0 *
b0 )
b0 (
b0 '
b0 &
b0 %
b0 $
b0 #
b0 "
b0 !
$end
#10000
b11010010 L
b11010010 A
b100 6
b100 +
b10011010010 "
b10011010010 $
#20000
b101110 M
b10110 B
b101110 7
b10110 ,
b0 L
b0 A
b0 6
b0 +
b1011000101110 #
b1011000101110 %
b0 "
b0 $
#30000
b1111111111111111 !
b1111111111111111 *
b11111111 )
b11111111 N
b11111111 '
b11111111 8
b1 M
b0 B
b1 7
b0 ,
b11111111 L
b11111111 A
b11111111 6
b11111111 +
b1 #
b1 %
b1111111111111111 "
b1111111111111111 $
#40000
b1111111111111111 !
b1111111111111111 *
b11111111 )
b11111111 N
b11111111 (
b11111111 C
b0 '
b0 8
b11111111 M
b11111111 B
b11111111 7
b11111111 ,
b1 L
b1 A
b0 6
b0 +
b1111111111111111 #
b1111111111111111 %
b1 "
b1 $
#50000
b1111111000000001 )
b1111111000000001 N
b1111111000000001 (
b1111111000000001 C
b11111111111111100000000000000001 !
b11111111111111100000000000000001 *
b1111111000000001 '
b1111111000000001 8
b1111111000000001 &
b1111111000000001 -
b11111111 L
b11111111 A
b11111111 6
b11111111 +
b1111111111111111 "
b1111111111111111 $
#60000
b100 !
b100 *
b100 )
b100 N
b0 (
b0 C
b0 '
b0 8
b0 &
b0 -
b10 M
b0 B
b10 7
b0 ,
b10 L
b10 A
b0 6
b0 +
b10 #
b10 %
b10 "
b10 $
#70000
b0 )
b0 N
b10000000000000000 !
b10000000000000000 *
b1 &
b1 -
b0 M
b1 B
b0 7
b1 ,
b0 L
b0 A
b1 6
b1 +
b100000000 #
b100000000 %
b100000000 "
b100000000 $
#80000
b100000000000000000000 !
b100000000000000000000 *
b10000 &
b10000 -
b100 B
b100 ,
b100 6
b100 +
b10000000000 #
b10000000000 %
b10000000000 "
b10000000000 $
#90000
b111000111000110001110001110010 !
b111000111000110001110001110010 *
b11100001110010 )
b11100001110010 N
b11100001110010 (
b11100001110010 C
b11100001110010 '
b11100001110010 8
b11100001110010 &
b11100001110010 -
b10101010 M
b10101010 B
b10101010 7
b10101010 ,
b1010101 L
b1010101 A
b1010101 6
b1010101 +
b1010101010101010 #
b1010101010101010 %
b101010101010101 "
b101010101010101 $
