ArithmeticUnit/unsigned_div.v
module unsigned_div(
    input [15:0]dividend,
    input [15:0]divisor,
    output reg [15:0]quotient, 
    output reg [15:0]remainder
    );

    integer i;
    reg [16:0]remainder_stages[0:16];
    reg [15:0]quotient_stages[0:16];
    reg [16:0]temp_remainder[0:15];
    reg [16:0]temp_sub[0:15];

    always @(*)begin

        remainder_stages[0] = 17'b0;
        quotient_stages[0] = dividend;

        for (i = 0; i < 16; i = i + 1)begin

            temp_remainder[i] = {remainder_stages[i][15:0], quotient_stages[i][15]};
            temp_sub[i] = temp_remainder[i] - {1'b0, divisor};

            if (temp_sub[i][16] == 1'b0)begin
                remainder_stages[i + 1] = temp_sub[i];
                quotient_stages[i + 1] = {quotient_stages[i][14:0], 1'b1};
            end else begin
                remainder_stages[i + 1] = temp_remainder[i];
                quotient_stages[i + 1] = quotient_stages[i] << 1;
            end
        end
        quotient = quotient_stages[16];
        remainder = remainder_stages[16][15:0];
    end
endmodule

ArithmeticUnit/tb_unsigned_div.v
`timescale 1ns/1ps

module tb_unsigned_div();
    reg [15:0]dividend;
    reg [15:0]divisor;
    wire [15:0]quotient;
    wire [15:0]remainder;

    unsigned_div uut (
        .dividend(dividend),
        .divisor(divisor),
        .quotient(quotient),
        .remainder(remainder)
    );

    initial begin
        $dumpfile("unsignedwaveform.vcd");
        $dumpvars(0, tb_unsigned_div);

        dividend = 16'd100;
        divisor = 16'd10;
        #10;
        $display("input 1 = %b input 2 = %b || quotient = %b || remainder = %b", dividend, divisor, quotient, remainder);

        dividend = 16'd103;
        divisor = 16'd10;
        #10;
        $display("input 1 = %b input 2 = %b || quotient = %b || remainder = %b", dividend, divisor, quotient, remainder);

        dividend = 16'd50;
        divisor = 16'd0;
        #10;
        $display("input 1 = %b input 2 = %b || quotient = %b || remainder = %b", dividend, divisor, quotient, remainder);

        dividend = 16'd12345;
        divisor = 16'd1;
        #10;
        $display("input 1 = %b input 2 = %b || quotient = %b || remainder = %b", dividend, divisor, quotient, remainder);

        dividend = 16'd0;
        divisor = 16'd12345;
        #10;
        $display("input 1 = %b input 2 = %b || quotient = %b || remainder = %b", dividend, divisor, quotient, remainder);

        dividend = 16'd50;
        divisor = 16'd100;
        #10;
        $display("input 1 = %b input 2 = %b || quotient = %b || remainder = %b", dividend, divisor, quotient, remainder);

        dividend = 16'd4321;
        divisor = 16'd4321;
        #10;
        $display("input 1 = %b input 2 = %b || quotient = %b || remainder = %b", dividend, divisor, quotient, remainder);

        dividend = 16'hFFFF;
        divisor = 16'd2;
        #10;
        $display("input 1 = %b input 2 = %b || quotient = %b || remainder = %b", dividend, divisor, quotient, remainder);

        dividend = 16'hFFFF;
        divisor = 16'hFFFF;
        #10;
        $display("input 1 = %b input 2 = %b || quotient = %b || remainder = %b", dividend, divisor, quotient, remainder);

        $finish;
    end
endmodule

unsignedwaveform.vcd
$date
	Thu Jul 31 03:30:07 2025
$end
$version
	Icarus Verilog
$end
$timescale
	1ps
$end
$scope module tb_unsigned_div $end
$var wire 16 ! remainder [15:0] $end
$var wire 16 " quotient [15:0] $end
$var reg 16 # dividend [15:0] $end
$var reg 16 $ divisor [15:0] $end
$scope module uut $end
$var wire 16 % dividend [15:0] $end
$var wire 16 & divisor [15:0] $end
$var reg 16 ' quotient [15:0] $end
$var reg 16 ( remainder [15:0] $end
$var integer 32 ) i [31:0] $end
$upscope $end
$upscope $end
$enddefinitions $end
$comment Show the parameter values. $end
$dumpall
$end
#0
$dumpvars
b10000 )
b0 (
b1010 '
b1010 &
b1100100 %
b1010 $
b1100100 #
b1010 "
b0 !
$end
#10000
b11 !
b11 (
b10000 )
b1100111 #
b1100111 %
#20000
b110010 !
b110010 (
b1111111111111111 "
b1111111111111111 '
b10000 )
b0 $
b0 &
b110010 #
b110010 %
#30000
b0 !
b0 (
b11000000111001 "
b11000000111001 '
b10000 )
b1 $
b1 &
b11000000111001 #
b11000000111001 %
#40000
b0 "
b0 '
b10000 )
b11000000111001 $
b11000000111001 &
b0 #
b0 %
#50000
b110010 !
b110010 (
b10000 )
b1100100 $
b1100100 &
b110010 #
b110010 %
#60000
b0 !
b0 (
b1 "
b1 '
b10000 )
b1000011100001 $
b1000011100001 &
b1000011100001 #
b1000011100001 %
#70000
b1 !
b1 (
b111111111111111 "
b111111111111111 '
b10000 )
b10 $
b10 &
b1111111111111111 #
b1111111111111111 %
#80000
b0 !
b0 (
b1 "
b1 '
b10000 )
b1111111111111111 $
b1111111111111111 &
